torchpwl/__init__.py
torchpwl/pwl.py
torchpwl/pwl_test.py
torchpwl-0.2.0.dist-info/LICENSE
torchpwl-0.2.0.dist-info/METADATA
torchpwl-0.2.0.dist-info/WHEEL
torchpwl-0.2.0.dist-info/top_level.txt
torchpwl-0.2.0.dist-info/RECORD
