Metadata-Version: 2.1
Name: torchpwl
Version: 0.2.0
Summary: Implementation of Piecewise Linear Functions (PWL) in PyTorch.
Home-page: https://github.com/PiotrDabkowski/torchpwl
Author: Piotr Dabkowski
Author-email: piodrus@gmail.com
License: MIT
Platform: UNKNOWN
Requires-Dist: torch (>=1.1.0)
